ravbar/__init__.py
ravbar/frontend/build/asset-manifest.json
ravbar/frontend/build/bootstrap.min.css
ravbar/frontend/build/index.html
ravbar/frontend/build/precache-manifest.bc36316c153a9944056245e6e8f83371.js
ravbar/frontend/build/service-worker.js
ravbar/frontend/build/static/css/main.d9e4b44e.chunk.css
ravbar/frontend/build/static/css/main.d9e4b44e.chunk.css.map
ravbar/frontend/build/static/js/2.5c88d1c5.chunk.js
ravbar/frontend/build/static/js/2.5c88d1c5.chunk.js.LICENSE.txt
ravbar/frontend/build/static/js/2.5c88d1c5.chunk.js.map
ravbar/frontend/build/static/js/main.46c6351c.chunk.js
ravbar/frontend/build/static/js/main.46c6351c.chunk.js.map
ravbar/frontend/build/static/js/runtime-main.4bd7b106.js
ravbar/frontend/build/static/js/runtime-main.4bd7b106.js.map
ravbar-0.0.1.dist-info/LICENSE
ravbar-0.0.1.dist-info/METADATA
ravbar-0.0.1.dist-info/WHEEL
ravbar-0.0.1.dist-info/top_level.txt
ravbar-0.0.1.dist-info/RECORD
