Metadata-Version: 2.1
Name: ravbar
Version: 0.0.1
Summary: navbar
Home-page: UNKNOWN
Author: Ravish Rawal
Author-email: ravish.rawal@columbia.edu
License: UNKNOWN
Platform: UNKNOWN
Requires-Python: >=3.6
Requires-Dist: streamlit (>=0.63)
